enthought_sphinx_theme/__init__.py
enthought_sphinx_theme/enthought/layout.html
enthought_sphinx_theme/enthought/sourcelink.html
enthought_sphinx_theme/enthought/theme.conf
enthought_sphinx_theme/enthought/static/enthought.css_t
enthought_sphinx_theme/enthought/static/css/pygments.css
enthought_sphinx_theme/enthought/static/css/spc-bootstrap.css
enthought_sphinx_theme/enthought/static/css/spc-extend.css
enthought_sphinx_theme/enthought/static/fonts/SourceCodePro-Regular.otf.woff
enthought_sphinx_theme/enthought/static/fonts/SourceCodePro-Semibold.otf.woff
enthought_sphinx_theme/enthought/static/fonts/poppins-v19-latin-600.woff2
enthought_sphinx_theme/enthought/static/fonts/poppins-v19-latin-600italic.woff2
enthought_sphinx_theme/enthought/static/fonts/poppins-v19-latin-italic.woff2
enthought_sphinx_theme/enthought/static/fonts/poppins-v19-latin-regular.woff2
enthought_sphinx_theme/enthought/static/img/contents.png
enthought_sphinx_theme/enthought/static/img/e-logo.png
enthought_sphinx_theme/enthought/static/img/favicon.png
enthought_sphinx_theme/enthought/static/img/glyphicons-halflings-white.png
enthought_sphinx_theme/enthought/static/img/glyphicons-halflings.png
enthought_sphinx_theme/enthought/static/img/navigation.png
enthought_sphinx_theme/enthought/static/img/transparent-pixel.gif
enthought_sphinx_theme/enthought/static/img/ui-anim_basic_16x16.gif
enthought_sphinx_theme/enthought/static/js/copybutton.js
enthought_sphinx_theme/enthought/static/js/wrap_on_dot.js
enthought_sphinx_theme-0.7.3.dist-info/LICENSE
enthought_sphinx_theme-0.7.3.dist-info/METADATA
enthought_sphinx_theme-0.7.3.dist-info/WHEEL
enthought_sphinx_theme-0.7.3.dist-info/top_level.txt
enthought_sphinx_theme-0.7.3.dist-info/RECORD
