Metadata-Version: 2.1
Name: enthought_sphinx_theme
Version: 0.7.3
Summary: Sphinx theme for Enthought products
Home-page: https://github.com/enthought/enthought-sphinx-theme
Author: Enthought, Inc.
Author-email: info@enthought.com
License: BSD
Classifier: Development Status :: 4 - Beta
Classifier: Intended Audience :: Developers
Classifier: License :: OSI Approved :: BSD License
Classifier: Operating System :: OS Independent
Classifier: Topic :: Documentation
Classifier: Topic :: Software Development :: Documentation
License-File: LICENSE
